template/__init__.py
template/admin.py
template/apps.py
template/common_text.py
template/models.py
template/urls.py
template/filters/__init__.py
template/filters/filter_template.py
template/migrations/0001_initial.py
template/migrations/__init__.py
template/serializers/__init__.py
template/serializers/serializer_base.py
template/serializers/serializer_template.py
template/tasks/__init__.py
template/tasks/tasks_template.py
template/views/__init__.py
template/views/view_template.py
tests/__init__.py
tests/conftest.py
tests/fixtures/__init__.py
tests/fixtures/fixtures_common.py
tests/views/__init__.py
tests/views/test_template.py
django_template_backend-1.0.dist-info/LICENSE
django_template_backend-1.0.dist-info/METADATA
django_template_backend-1.0.dist-info/WHEEL
django_template_backend-1.0.dist-info/top_level.txt
django_template_backend-1.0.dist-info/RECORD
