Metadata-Version: 2.1
Name: django-template-backend
Version: 1.0
Summary: Django Template Backend
Home-page: https://github.com/personal-server/django-template-backend
Author: Sheldon Woodward
Author-email: me@sheldonw.com
License: MIT
Keywords: django backend
Platform: UNKNOWN
Classifier: Development Status :: 3 - Alpha
Classifier: Framework :: Django :: 2.2
Classifier: License :: OSI Approved :: MIT License
Classifier: Intended Audience :: Developers
Classifier: Topic :: Internet :: WWW/HTTP :: Session
Classifier: Programming Language :: Python :: 3
Classifier: Programming Language :: Python :: 3.8
Requires-Python: ~=3.8
Requires-Dist: django (~=2.2)
Requires-Dist: djangorestframework (~=3.11)
Requires-Dist: django-filter (~=2.3)
Requires-Dist: celery (~=5.0)
